aiondao/__init__.py
aiondao/__main__.py
aiondao/_imports.py
aiondao/agents/__init__.py
aiondao/agents/banking.py
aiondao/agents/commons.py
aiondao/agents/dummy.py
aiondao/agents/members.py
aiondao/agents/random_walk.py
aiondao/cli.py
aiondao/config.py
aiondao/dev.py
aiondao/economy.py
aiondao/hatch.py
aiondao/interfaces/__init__.py
aiondao/interfaces/access.py
aiondao/interfaces/models.py
aiondao/interfaces/networks.py
aiondao/interfaces/partials.py
aiondao/interfaces/policy.py
aiondao/interfaces/simulate.py
aiondao/libs/__init__.py
aiondao/libs/abcurve.py
aiondao/libs/bootloader.py
aiondao/libs/conviction.py
aiondao/libs/graph.py
aiondao/libs/monitors.py
aiondao/libs/pipes.py
aiondao/libs/states.py
aiondao/policies/__init__.py
aiondao/policies/_old_.py
aiondao/policies/_participants.py
aiondao/policies/participants.py
aiondao/policies/transformer.py
aiondao/schemas.py
aiondao/simulation.py
aiondao/utils/__init__.py
aiondao/utils/_utilz.py
aiondao/utils/mixins.py
aiondao/utils/networking.py
aiondao/utils/score.py
aiondao-0.1.1.dist-info/entry_points.txt
aiondao-0.1.1.dist-info/WHEEL
aiondao-0.1.1.dist-info/METADATA
aiondao-0.1.1.dist-info/RECORD
